search_in_api/__init__.py
search_in_api/search_in_api.py
search_in_api-1.0.1.dist-info/AUTHORS.rst
search_in_api-1.0.1.dist-info/LICENSE
search_in_api-1.0.1.dist-info/METADATA
search_in_api-1.0.1.dist-info/WHEEL
search_in_api-1.0.1.dist-info/entry_points.txt
search_in_api-1.0.1.dist-info/top_level.txt
search_in_api-1.0.1.dist-info/RECORD
