Metadata-Version: 2.1
Name: search-in-api
Version: 1.0.1
Summary: Search in API is a script that allows you to search among multiple pages of an API endpoint.
Home-page: https://github.com/archatas/search_in_api
Author: Aidas Bendoraitis
Author-email: aidasbend@yahoo.com
License: MIT license
Keywords: search_in_api
Platform: UNKNOWN
Classifier: Development Status :: 5 - Production/Stable
Classifier: Intended Audience :: Developers
Classifier: License :: OSI Approved :: MIT License
Classifier: Natural Language :: English
Classifier: Programming Language :: Python :: 3
Classifier: Programming Language :: Python :: 3.4
Classifier: Programming Language :: Python :: 3.5
Classifier: Programming Language :: Python :: 3.6
Classifier: Programming Language :: Python :: 3.7
Classifier: Programming Language :: Python :: 3.8
Requires-Dist: altgraph (==0.17)
Requires-Dist: asn1crypto (==1.3.0)
Requires-Dist: certifi (==2019.11.28)
Requires-Dist: cffi (==1.13.2)
Requires-Dist: chardet (==3.0.4)
Requires-Dist: cryptography (==2.8)
Requires-Dist: dis3 (==0.1.3)
Requires-Dist: future (==0.18.2)
Requires-Dist: idna (==2.8)
Requires-Dist: ipaddress (==1.0.23)
Requires-Dist: macholib (==1.14)
Requires-Dist: pefile (==2019.4.18)
Requires-Dist: pycparser (==2.19)
Requires-Dist: PyInstaller (==3.6)
Requires-Dist: pyOpenSSL (==19.1.0)
Requires-Dist: requests (>=2.22.0)
Requires-Dist: urllib3 (>=1.25.8)
